simplemailsender/__init__.py
simplemailsender/simplemailsender.py
simplemailsender-0.4.0.dist-info/LICENSE
simplemailsender-0.4.0.dist-info/METADATA
simplemailsender-0.4.0.dist-info/WHEEL
simplemailsender-0.4.0.dist-info/top_level.txt
simplemailsender-0.4.0.dist-info/RECORD
