Metadata-Version: 2.1
Name: simplemailsender
Version: 0.4.0
Summary: A simple mail sender.
Home-page: https://github.com/aburgoscimne/simplemailsender
Author: Alberto Burgos Plaza
Author-email: albertoburgosplaza@gmail.com
License: Apache
Keywords: e-mail
Requires-Python: >=3.8
License-File: LICENSE
